nbtof/__init__.py
nbtof/nbtof_base.py
nbtof/nbtof_concat.py
nbtof/nbtof_generate.py
nbtof-0.0.8.dist-info/LICENSE
nbtof-0.0.8.dist-info/METADATA
nbtof-0.0.8.dist-info/WHEEL
nbtof-0.0.8.dist-info/top_level.txt
nbtof-0.0.8.dist-info/RECORD
