Metadata-Version: 2.1
Name: nbtof
Version: 0.0.8
Summary: nbtof: transfering notebook to function
Home-page: https://github.com/Nodaka/nbtof
Download-URL: https://github.com/Nodaka/nbtof
Author: Haruka Nodaka
Author-email: haruka.nodaka@gmail.com
Maintainer: Haruka Nodaka
Maintainer-email: haruka.nodaka@gmail.com
License: MIT
Classifier: License :: OSI Approved :: MIT License
Classifier: Operating System :: OS Independent
Classifier: Programming Language :: Python :: 3
Classifier: Topic :: Software Development :: Code Generators
Classifier: Framework :: Jupyter
Requires-Python: >=3.9
License-File: LICENSE
